setup.py
learnbysubs/__init__.py
learnbysubs/texts.py
learnbysubs.egg-info/PKG-INFO
learnbysubs.egg-info/SOURCES.txt
learnbysubs.egg-info/dependency_links.txt
learnbysubs.egg-info/entry_points.txt
learnbysubs.egg-info/requires.txt
learnbysubs.egg-info/top_level.txt