Metadata-Version: 1.1
Name: learnbysubs
Version: 0.1
Summary: Generate combined subtitle file with two different languages
Home-page: https://github.com/hakanzy/learnbysubs
Author: Hakan OZAY
Author-email: hakanzy@gmail.com
License: UNKNOWN
Platform: UNKNOWN
Classifier: Development Status :: 4 - Beta
Classifier: Environment :: Console
Classifier: Intended Audience :: Developers
Classifier: License :: OSI Approved :: BSD License
Classifier: Operating System :: OS Independent
Classifier: Programming Language :: Python
